MergeTicketingClient/__init__.py
MergeTicketingClient/api_client.py
MergeTicketingClient/configuration.py
MergeTicketingClient/exceptions.py
MergeTicketingClient/model_utils.py
MergeTicketingClient/rest.py
MergeTicketingClient/api/__init__.py
MergeTicketingClient/api/account_details_api.py
MergeTicketingClient/api/account_token_api.py
MergeTicketingClient/api/accounts_api.py
MergeTicketingClient/api/attachments_api.py
MergeTicketingClient/api/available_actions_api.py
MergeTicketingClient/api/collections_api.py
MergeTicketingClient/api/comments_api.py
MergeTicketingClient/api/contacts_api.py
MergeTicketingClient/api/delete_account_api.py
MergeTicketingClient/api/force_resync_api.py
MergeTicketingClient/api/generate_key_api.py
MergeTicketingClient/api/issues_api.py
MergeTicketingClient/api/link_token_api.py
MergeTicketingClient/api/linked_accounts_api.py
MergeTicketingClient/api/passthrough_api.py
MergeTicketingClient/api/projects_api.py
MergeTicketingClient/api/regenerate_key_api.py
MergeTicketingClient/api/selective_sync_api.py
MergeTicketingClient/api/sync_status_api.py
MergeTicketingClient/api/tags_api.py
MergeTicketingClient/api/teams_api.py
MergeTicketingClient/api/tickets_api.py
MergeTicketingClient/api/users_api.py
MergeTicketingClient/api/webhook_receivers_api.py
MergeTicketingClient/apis/__init__.py
MergeTicketingClient/model/__init__.py
MergeTicketingClient/model/account.py
MergeTicketingClient/model/account_details.py
MergeTicketingClient/model/account_details_and_actions.py
MergeTicketingClient/model/account_details_and_actions_integration.py
MergeTicketingClient/model/account_details_and_actions_status_enum.py
MergeTicketingClient/model/account_integration.py
MergeTicketingClient/model/account_token.py
MergeTicketingClient/model/attachment.py
MergeTicketingClient/model/attachment_request.py
MergeTicketingClient/model/available_actions.py
MergeTicketingClient/model/categories_enum.py
MergeTicketingClient/model/category_enum.py
merge_ticketing_client-1.1.2.dist-info/LICENSE.md
merge_ticketing_client-1.1.2.dist-info/METADATA
merge_ticketing_client-1.1.2.dist-info/WHEEL
merge_ticketing_client-1.1.2.dist-info/top_level.txt
merge_ticketing_client-1.1.2.dist-info/RECORD
