Metadata-Version: 2.1
Name: merge-ticketing-client
Version: 1.1.2
Summary: Merge Ticketing API
Home-page: 
Author: Merge Team
Author-email: hello@merge.dev
Keywords: OpenAPI,OpenAPI-Generator,Merge Ticketing API
Requires-Python: >=3.6
License-File: LICENSE.md
Requires-Dist: urllib3 (>=1.25.3)
Requires-Dist: python-dateutil
